juxtorpus/__init__.py
juxtorpus/constants.py
juxtorpus/features/__init__.py
juxtorpus/features/keywords.py
juxtorpus/features/polarity.py
juxtorpus/features/similarity.py
juxtorpus/features/zipf.py
juxtorpus/jux.py
juxtorpus/stats/__init__.py
juxtorpus/stats/loglikelihood_effectsize.py
juxtorpus/stats/stats.py
juxtorpus/utils/__init__.py
juxtorpus/utils/deduplicated_dir.py
juxtorpus/utils/utils_ipywidgets.py
juxtorpus/viz/__init__.py
juxtorpus/viz/corpus.py
juxtorpus/viz/item_timeline.py
juxtorpus/viz/polarity_bar.py
juxtorpus/viz/polarity_wordcloud.py
juxtorpus/viz/style/__init__.py
juxtorpus/viz/style/ipyw.py
juxtorpus/viz/vocab_timeline.py
juxtorpus-0.3.2.dist-info/METADATA
juxtorpus-0.3.2.dist-info/WHEEL
juxtorpus-0.3.2.dist-info/RECORD
